[
   {
      "id": 1,
      "image": "https://placekitten.com/301/301"
   },
   {
      "id": 2,
      "image": "https://placekitten.com/314/314"
   },
   {
      "id": 3,
      "image": "https://placekitten.com/303/303"
   },
   {
      "id": 4,
      "image": "https://placekitten.com/304/304"
   },
   {
      "id": 5,
      "image": "https://placekitten.com/305/305"
   },
   {
      "id": 6,
      "image": "https://placekitten.com/306/306"
   },
   {
      "id": 7,
      "image": "https://placekitten.com/307/307"
   },
   {
      "id": 8,
      "image": "https://placekitten.com/308/308"
   },
   {
      "id": 9,
      "image": "https://placekitten.com/316/316"
   },
   {
      "id": 10,
      "image": "https://placekitten.com/310/310"
   },
   {
      "id": 11,
      "image": "https://placekitten.com/320/320"
   },
   {
      "id": 12,
      "image": "https://placekitten.com/312/312"
   }
]